intake_mcp_server/__init__.py
intake_mcp_server/__version__.py
intake_mcp_server/server.py
intake_mcp_server-0.0.1.dist-info/METADATA
intake_mcp_server-0.0.1.dist-info/WHEEL
intake_mcp_server-0.0.1.dist-info/licenses/LICENSE
intake_mcp_server-0.0.1.dist-info/RECORD
